ibm_apidocs_cli/__init__.py
ibm_apidocs_cli/main.py
ibm_apidocs_cli/version.py
ibm_apidocs_cli-0.19.0.dist-info/METADATA
ibm_apidocs_cli-0.19.0.dist-info/WHEEL
ibm_apidocs_cli-0.19.0.dist-info/entry_points.txt
ibm_apidocs_cli-0.19.0.dist-info/top_level.txt
ibm_apidocs_cli-0.19.0.dist-info/zip-safe
ibm_apidocs_cli-0.19.0.dist-info/RECORD
