Metadata-Version: 2.1
Name: ibm-apidocs-cli
Version: 0.19.0
Summary: CLI library to automate the API Reference generation
Home-page: https://cloud.ibm.com/apidocs
Author: IBM Corp
Author-email: germanatt@us.ibm.com
License: MIT
Keywords: api-reference,ibm-watson,ibm-cloud
Classifier: Programming Language :: Python
Classifier: Programming Language :: Python :: 2
Classifier: Programming Language :: Python :: 3
Classifier: Development Status :: 4 - Beta
Classifier: Intended Audience :: Developers
Classifier: Operating System :: OS Independent
Classifier: Topic :: Software Development :: Libraries :: Python Modules
Classifier: Topic :: Software Development :: Libraries :: Application Frameworks
Requires-Dist: requests <3.0,>=2.0
Requires-Dist: outdated >=0.2.0
Requires-Dist: lxml ==4.3.2
Requires-Dist: PyYAML ==3.13
